carbonsh/Config.py
carbonsh/__init__.py
carbonsh/carbonsh.py
carbonsh/utils.py
carbonsh/constants/__init__.py
carbonsh/constants/controls.py
carbonsh/constants/escales.py
carbonsh/constants/fonts.py
carbonsh/constants/languages.py
carbonsh/constants/themes.py
tests/__init__.py
tests/test_carbonsh.py
tests/test_config.py
carbonsh-0.2.0.dist-info/LICENSE
carbonsh-0.2.0.dist-info/METADATA
carbonsh-0.2.0.dist-info/WHEEL
carbonsh-0.2.0.dist-info/top_level.txt
carbonsh-0.2.0.dist-info/RECORD
