Metadata-Version: 2.1
Name: carbonsh
Version: 0.2.0
Summary: carbon.now.sh python module
Home-page: https://github.com/MrMarble/carbonsh
Author: MrMarble
Author-email: alvarotinocomarmol@gmail.com
License: GPL-3.0-or-later
Platform: UNKNOWN
Classifier: Intended Audience :: Developers
Classifier: License :: OSI Approved :: GNU General Public License v3 or later (GPLv3+)
Classifier: Natural Language :: English
Classifier: Programming Language :: Python :: 3
Classifier: Programming Language :: Python :: 3.6
Classifier: Programming Language :: Python :: 3.7
Classifier: Programming Language :: Python :: 3.8
Requires-Python: >=3.6<4
License-File: LICENSE
Requires-Dist: pyppeteer (>=0.2.2<1)
